{
  "name": "Pocket Dimension",
  "description": "Teleport in and out of your own personal pocket dimension!",
  "cooldown": 10,
  "hud_render": {
    "should_render": true,
    "bar_index": 7,
    "sprite_location": "origins:textures/gui/community/spiderkolo/resource_bar_03.png"
  },
  "key": {
    "key": "key.origins.secondary_active"
  },

  "type": "origins:active_self",
  "entity_action": {
    "type": "origins:if_else",
    "condition": {
      "type": "origins:and",
      "conditions": [
        {
          "type": "origins:dimension",
          "dimension": "limeorigins:pocket_dim_1",
          "inverted": true
        },
        {
          "type": "origins:dimension",
          "dimension": "limeorigins:pocket_dim_2",
          "inverted": true
        },
        {
          "type": "origins:dimension",
          "dimension": "limeorigins:pocket_dim_3",
          "inverted": true
        },
        {
          "type": "origins:dimension",
          "dimension": "limeorigins:pocket_dim_4",
          "inverted": true
        },
        {
          "type": "origins:dimension",
          "dimension": "limeorigins:pocket_dim_5",
          "inverted": true
        },
        {
          "type": "origins:dimension",
          "dimension": "limeorigins:pocket_dim_6",
          "inverted": true
        },
        {
          "type": "origins:dimension",
          "dimension": "limeorigins:pocket_dim_7",
          "inverted": true
        },
        {
          "type": "origins:dimension",
          "dimension": "limeorigins:pocket_dim_8",
          "inverted": true
        },
        {
          "type": "origins:dimension",
          "dimension": "limeorigins:pocket_dim_9",
          "inverted": true
        },
        {
          "type": "origins:dimension",
          "dimension": "limeorigins:pocket_dim_10",
          "inverted": true
        },
        {
          "type": "origins:dimension",
          "dimension": "limeorigins:pocket_dim_11",
          "inverted": true
        },
        {
          "type": "origins:dimension",
          "dimension": "limeorigins:pocket_dim_12",
          "inverted": true
        },
        {
          "type": "origins:dimension",
          "dimension": "limeorigins:pocket_dim_13",
          "inverted": true
        },
        {
          "type": "origins:dimension",
          "dimension": "limeorigins:pocket_dim_14",
          "inverted": true
        },
        {
          "type": "origins:dimension",
          "dimension": "limeorigins:pocket_dim_15",
          "inverted": true
        },
        {
          "type": "origins:dimension",
          "dimension": "limeorigins:pocket_dim_16",
          "inverted": true
        },
        {
          "type": "origins:dimension",
          "dimension": "limeorigins:pocket_dim_17",
          "inverted": true
        },
        {
          "type": "origins:dimension",
          "dimension": "limeorigins:pocket_dim_18",
          "inverted": true
        },
        {
          "type": "origins:dimension",
          "dimension": "limeorigins:pocket_dim_19",
          "inverted": true
        },
        {
          "type": "origins:dimension",
          "dimension": "limeorigins:pocket_dim_20",
          "inverted": true
        }
      ]
    },

    "if_action": {
      "type": "origins:and",
      "actions": [
        {
          "type": "origins:play_sound",
          "sound": "minecraft:entity.enderman.teleport"
        },
        {
          "type": "origins:if_else",
          "condition": {
            "type": "origins:scoreboard",
            "objective": "dim_owned",
            "comparison": "==",
            "compare_to": 0
          },

          "if_action": {
            "type": "origins:if_else_list",
            "actions": [
              {
                "condition": {
                  "type": "origins:and",
                  "conditions": [
                    {
                      "type": "origins:scoreboard",
                      "objective": "dim_owned",
                      "comparison": "==",
                      "compare_to": 0
                    },
                    {
                      "type": "origins:command",
                      "command": "execute if score #global dim_1 matches 0",
                      "comparison": "==",
                      "compare_to": 1
                    }
                  ]
                },
                "action": {
                  "type": "origins:execute_command",
                  "command": "function limeorigins:dimcreate1"
                }
              },
              {
                "condition": {
                  "type": "origins:and",
                  "conditions": [
                    {
                      "type": "origins:scoreboard",
                      "objective": "dim_owned",
                      "comparison": "==",
                      "compare_to": 0
                    },
                    {
                      "type": "origins:command",
                      "command": "execute if score #global dim_2 matches 0",
                      "comparison": "==",
                      "compare_to": 1
                    }
                  ]
                },
                "action": {
                  "type": "origins:execute_command",
                  "command": "function limeorigins:dimcreate2"
                }
              },
              {
                "condition": {
                  "type": "origins:and",
                  "conditions": [
                    {
                      "type": "origins:scoreboard",
                      "objective": "dim_owned",
                      "comparison": "==",
                      "compare_to": 0
                    },
                    {
                      "type": "origins:command",
                      "command": "execute if score #global dim_3 matches 0",
                      "comparison": "==",
                      "compare_to": 1
                    }
                  ]
                },
                "action": {
                  "type": "origins:execute_command",
                  "command": "function limeorigins:dimcreate3"
                }
              },
              {
                "condition": {
                  "type": "origins:and",
                  "conditions": [
                    {
                      "type": "origins:scoreboard",
                      "objective": "dim_owned",
                      "comparison": "==",
                      "compare_to": 0
                    },
                    {
                      "type": "origins:command",
                      "command": "execute if score #global dim_4 matches 0",
                      "comparison": "==",
                      "compare_to": 1
                    }
                  ]
                },
                "action": {
                  "type": "origins:execute_command",
                  "command": "function limeorigins:dimcreate4"
                }
              },
              {
                "condition": {
                  "type": "origins:and",
                  "conditions": [
                    {
                      "type": "origins:scoreboard",
                      "objective": "dim_owned",
                      "comparison": "==",
                      "compare_to": 0
                    },
                    {
                      "type": "origins:command",
                      "command": "execute if score #global dim_5 matches 0",
                      "comparison": "==",
                      "compare_to": 1
                    }
                  ]
                },
                "action": {
                  "type": "origins:execute_command",
                  "command": "function limeorigins:dimcreate5"
                }
              },
              {
                "condition": {
                  "type": "origins:and",
                  "conditions": [
                    {
                      "type": "origins:scoreboard",
                      "objective": "dim_owned",
                      "comparison": "==",
                      "compare_to": 0
                    },
                    {
                      "type": "origins:command",
                      "command": "execute if score #global dim_6 matches 0",
                      "comparison": "==",
                      "compare_to": 1
                    }
                  ]
                },
                "action": {
                  "type": "origins:execute_command",
                  "command": "function limeorigins:dimcreate6"
                }
              },
              {
                "condition": {
                  "type": "origins:and",
                  "conditions": [
                    {
                      "type": "origins:scoreboard",
                      "objective": "dim_owned",
                      "comparison": "==",
                      "compare_to": 0
                    },
                    {
                      "type": "origins:command",
                      "command": "execute if score #global dim_7 matches 0",
                      "comparison": "==",
                      "compare_to": 1
                    }
                  ]
                },
                "action": {
                  "type": "origins:execute_command",
                  "command": "function limeorigins:dimcreate7"
                }
              },
              {
                "condition": {
                  "type": "origins:and",
                  "conditions": [
                    {
                      "type": "origins:scoreboard",
                      "objective": "dim_owned",
                      "comparison": "==",
                      "compare_to": 0
                    },
                    {
                      "type": "origins:command",
                      "command": "execute if score #global dim_8 matches 0",
                      "comparison": "==",
                      "compare_to": 1
                    }
                  ]
                },
                "action": {
                  "type": "origins:execute_command",
                  "command": "function limeorigins:dimcreate8"
                }
              },
              {
                "condition": {
                  "type": "origins:and",
                  "conditions": [
                    {
                      "type": "origins:scoreboard",
                      "objective": "dim_owned",
                      "comparison": "==",
                      "compare_to": 0
                    },
                    {
                      "type": "origins:command",
                      "command": "execute if score #global dim_9 matches 0",
                      "comparison": "==",
                      "compare_to": 1
                    }
                  ]
                },
                "action": {
                  "type": "origins:execute_command",
                  "command": "function limeorigins:dimcreate9"
                }
              },
              {
                "condition": {
                  "type": "origins:and",
                  "conditions": [
                    {
                      "type": "origins:scoreboard",
                      "objective": "dim_owned",
                      "comparison": "==",
                      "compare_to": 0
                    },
                    {
                      "type": "origins:command",
                      "command": "execute if score #global dim_10 matches 0",
                      "comparison": "==",
                      "compare_to": 1
                    }
                  ]
                },
                "action": {
                  "type": "origins:execute_command",
                  "command": "function limeorigins:dimcreate10"
                }
              },
              {
                "condition": {
                  "type": "origins:and",
                  "conditions": [
                    {
                      "type": "origins:scoreboard",
                      "objective": "dim_owned",
                      "comparison": "==",
                      "compare_to": 0
                    },
                    {
                      "type": "origins:command",
                      "command": "execute if score #global dim_11 matches 0",
                      "comparison": "==",
                      "compare_to": 1
                    }
                  ]
                },
                "action": {
                  "type": "origins:execute_command",
                  "command": "function limeorigins:dimcreate11"
                }
              },
              {
                "condition": {
                  "type": "origins:and",
                  "conditions": [
                    {
                      "type": "origins:scoreboard",
                      "objective": "dim_owned",
                      "comparison": "==",
                      "compare_to": 0
                    },
                    {
                      "type": "origins:command",
                      "command": "execute if score #global dim_12 matches 0",
                      "comparison": "==",
                      "compare_to": 1
                    }
                  ]
                },
                "action": {
                  "type": "origins:execute_command",
                  "command": "function limeorigins:dimcreate12"
                }
              },
              {
                "condition": {
                  "type": "origins:and",
                  "conditions": [
                    {
                      "type": "origins:scoreboard",
                      "objective": "dim_owned",
                      "comparison": "==",
                      "compare_to": 0
                    },
                    {
                      "type": "origins:command",
                      "command": "execute if score #global dim_13 matches 0",
                      "comparison": "==",
                      "compare_to": 1
                    }
                  ]
                },
                "action": {
                  "type": "origins:execute_command",
                  "command": "function limeorigins:dimcreate13"
                }
              },
              {
                "condition": {
                  "type": "origins:and",
                  "conditions": [
                    {
                      "type": "origins:scoreboard",
                      "objective": "dim_owned",
                      "comparison": "==",
                      "compare_to": 0
                    },
                    {
                      "type": "origins:command",
                      "command": "execute if score #global dim_14 matches 0",
                      "comparison": "==",
                      "compare_to": 1
                    }
                  ]
                },
                "action": {
                  "type": "origins:execute_command",
                  "command": "function limeorigins:dimcreate14"
                }
              },
              {
                "condition": {
                  "type": "origins:and",
                  "conditions": [
                    {
                      "type": "origins:scoreboard",
                      "objective": "dim_owned",
                      "comparison": "==",
                      "compare_to": 0
                    },
                    {
                      "type": "origins:command",
                      "command": "execute if score #global dim_15 matches 0",
                      "comparison": "==",
                      "compare_to": 1
                    }
                  ]
                },
                "action": {
                  "type": "origins:execute_command",
                  "command": "function limeorigins:dimcreate15"
                }
              },
              {
                "condition": {
                  "type": "origins:and",
                  "conditions": [
                    {
                      "type": "origins:scoreboard",
                      "objective": "dim_owned",
                      "comparison": "==",
                      "compare_to": 0
                    },
                    {
                      "type": "origins:command",
                      "command": "execute if score #global dim_16 matches 0",
                      "comparison": "==",
                      "compare_to": 1
                    }
                  ]
                },
                "action": {
                  "type": "origins:execute_command",
                  "command": "function limeorigins:dimcreate16"
                }
              },
              {
                "condition": {
                  "type": "origins:and",
                  "conditions": [
                    {
                      "type": "origins:scoreboard",
                      "objective": "dim_owned",
                      "comparison": "==",
                      "compare_to": 0
                    },
                    {
                      "type": "origins:command",
                      "command": "execute if score #global dim_17 matches 0",
                      "comparison": "==",
                      "compare_to": 1
                    }
                  ]
                },
                "action": {
                  "type": "origins:execute_command",
                  "command": "function limeorigins:dimcreate17"
                }
              },
              {
                "condition": {
                  "type": "origins:and",
                  "conditions": [
                    {
                      "type": "origins:scoreboard",
                      "objective": "dim_owned",
                      "comparison": "==",
                      "compare_to": 0
                    },
                    {
                      "type": "origins:command",
                      "command": "execute if score #global dim_18 matches 0",
                      "comparison": "==",
                      "compare_to": 1
                    }
                  ]
                },
                "action": {
                  "type": "origins:execute_command",
                  "command": "function limeorigins:dimcreate18"
                }
              },
              {
                "condition": {
                  "type": "origins:and",
                  "conditions": [
                    {
                      "type": "origins:scoreboard",
                      "objective": "dim_owned",
                      "comparison": "==",
                      "compare_to": 0
                    },
                    {
                      "type": "origins:command",
                      "command": "execute if score #global dim_19 matches 0",
                      "comparison": "==",
                      "compare_to": 1
                    }
                  ]
                },
                "action": {
                  "type": "origins:execute_command",
                  "command": "function limeorigins:dimcreate19"
                }
              },
              {
                "condition": {
                  "type": "origins:and",
                  "conditions": [
                    {
                      "type": "origins:scoreboard",
                      "objective": "dim_owned",
                      "comparison": "==",
                      "compare_to": 0
                    },
                    {
                      "type": "origins:command",
                      "command": "execute if score #global dim_20 matches 0",
                      "comparison": "==",
                      "compare_to": 1
                    }
                  ]
                },
                "action": {
                  "type": "origins:execute_command",
                  "command": "function limeorigins:dimcreate20"
                }
              }
            ]
          },
          "else_action": {
            "type": "origins:if_else_list",
            "actions": [
              {
                "condition": {
                  "type": "origins:scoreboard",
                  "objective": "dim_owned",
                  "comparison": "==",
                  "compare_to": 1
                },
                "action": {
                    "type": "origins:and",
                    "actions": [
                      {
                        "type": "origins:execute_command",
                        "command": "summon marker ~ ~ ~ {Tags:[\"markerdim1\"]}"
                      },
                      {
                        "type": "origins:execute_command",
                        "command": "execute in limeorigins:pocket_dim_1 run tp @s 500 97 500"
                      }
                    ]
                  }
                },
              {
                "condition": {
                  "type": "origins:scoreboard",
                  "objective": "dim_owned",
                  "comparison": "==",
                  "compare_to": 2
                },
                "action": {
                  "type": "origins:and",
                    "actions": [
                      {
                        "type": "origins:execute_command",
                        "command": "summon marker ~ ~ ~ {Tags:[\"markerdim2\"]}"
                      },
                      {
                        "type": "origins:execute_command",
                        "command": "execute in limeorigins:pocket_dim_2 run tp @s 500 97 500"
                      }
                    ]
                  }
                },
              {
                "condition": {
                  "type": "origins:scoreboard",
                  "objective": "dim_owned",
                  "comparison": "==",
                  "compare_to": 3
                },
                "action": {
                  "type": "origins:and",
                    "actions": [
                      {
                        "type": "origins:execute_command",
                        "command": "summon marker ~ ~ ~ {Tags:[\"markerdim3\"]}"
                      },
                      {
                        "type": "origins:execute_command",
                        "command": "execute in limeorigins:pocket_dim_3 run tp @s 500 97 500"
                      }
                    ]
                  }
                },
              {
                "condition": {
                  "type": "origins:scoreboard",
                  "objective": "dim_owned",
                  "comparison": "==",
                  "compare_to": 4
                },
                "action": {
                  "type": "origins:and",
                    "actions": [
                      {
                        "type": "origins:execute_command",
                        "command": "summon marker ~ ~ ~ {Tags:[\"markerdim4\"]}"
                      },
                      {
                        "type": "origins:execute_command",
                        "command": "execute in limeorigins:pocket_dim_4 run tp @s 500 97 500"
                      }
                    ]
                  }
                },
              {
                "condition": {
                  "type": "origins:scoreboard",
                  "objective": "dim_owned",
                  "comparison": "==",
                  "compare_to": 5
                },
                "action": {
                  "type": "origins:and",
                    "actions": [
                      {
                        "type": "origins:execute_command",
                        "command": "summon marker ~ ~ ~ {Tags:[\"markerdim5\"]}"
                      },
                      {
                        "type": "origins:execute_command",
                        "command": "execute in limeorigins:pocket_dim_5 run tp @s 500 97 500"
                      }
                    ]
                  }
                },
              {
                "condition": {
                  "type": "origins:scoreboard",
                  "objective": "dim_owned",
                  "comparison": "==",
                  "compare_to": 6
                },
                "action": {
                  "type": "origins:and",
                    "actions": [
                      {
                        "type": "origins:execute_command",
                        "command": "summon marker ~ ~ ~ {Tags:[\"markerdim6\"]}"
                      },
                      {
                        "type": "origins:execute_command",
                        "command": "execute in limeorigins:pocket_dim_6 run tp @s 500 97 500"
                      }
                    ]
                  }
                },
              {
                "condition": {
                  "type": "origins:scoreboard",
                  "objective": "dim_owned",
                  "comparison": "==",
                  "compare_to": 7
                },
                "action": {
                  "type": "origins:and",
                  "actions": [
                    {
                      "type": "origins:execute_command",
                      "command": "summon marker ~ ~ ~ {Tags:[\"markerdim7\"]}"
                    },
                    {
                      "type": "origins:execute_command",
                      "command": "execute in limeorigins:pocket_dim_7 run tp @s 500 97 500"
                    }
                  ]
                }
              },
              {
                "condition": {
                  "type": "origins:scoreboard",
                  "objective": "dim_owned",
                  "comparison": "==",
                  "compare_to": 8
                },
                "action": {
                  "type": "origins:and",
                  "actions": [
                    {
                      "type": "origins:execute_command",
                      "command": "summon marker ~ ~ ~ {Tags:[\"markerdim8\"]}"
                    },
                    {
                      "type": "origins:execute_command",
                      "command": "execute in limeorigins:pocket_dim_8 run tp @s 500 97 500"
                    }
                  ]
                }
              },
              {
                "condition": {
                  "type": "origins:scoreboard",
                  "objective": "dim_owned",
                  "comparison": "==",
                  "compare_to": 9
                },
                "action": {
                  "type": "origins:and",
                  "actions": [
                    {
                      "type": "origins:execute_command",
                      "command": "summon marker ~ ~ ~ {Tags:[\"markerdim9\"]}"
                    },
                    {
                      "type": "origins:execute_command",
                      "command": "execute in limeorigins:pocket_dim_9 run tp @s 500 97 500"
                    }
                  ]
                }
              },
              {
                "condition": {
                  "type": "origins:scoreboard",
                  "objective": "dim_owned",
                  "comparison": "==",
                  "compare_to": 10
                },
                "action": {
                  "type": "origins:and",
                  "actions": [
                    {
                      "type": "origins:execute_command",
                      "command": "summon marker ~ ~ ~ {Tags:[\"markerdim10\"]}"
                    },
                    {
                      "type": "origins:execute_command",
                      "command": "execute in limeorigins:pocket_dim_10 run tp @s 500 97 500"
                    }
                  ]
                }
              },
              {
                "condition": {
                  "type": "origins:scoreboard",
                  "objective": "dim_owned",
                  "comparison": "==",
                  "compare_to": 11
                },
                "action": {
                  "type": "origins:and",
                    "actions": [
                      {
                        "type": "origins:execute_command",
                        "command": "summon marker ~ ~ ~ {Tags:[\"markerdim11\"]}"
                      },
                      {
                        "type": "origins:execute_command",
                        "command": "execute in limeorigins:pocket_dim_11 run tp @s 500 97 500"
                      }
                    ]
                  }
                },
              {
                "condition": {
                  "type": "origins:scoreboard",
                  "objective": "dim_owned",
                  "comparison": "==",
                  "compare_to": 12
                },
                "action": {
                  "type": "origins:and",
                  "actions": [
                    {
                      "type": "origins:execute_command",
                      "command": "summon marker ~ ~ ~ {Tags:[\"markerdim12\"]}"
                    },
                    {
                      "type": "origins:execute_command",
                      "command": "execute in limeorigins:pocket_dim_12 run tp @s 500 97 500"
                    }
                  ]
                }
              },
              {
                "condition": {
                  "type": "origins:scoreboard",
                  "objective": "dim_owned",
                  "comparison": "==",
                  "compare_to": 13
                },
                "action": {
                  "type": "origins:and",
                  "actions": [
                    {
                      "type": "origins:execute_command",
                      "command": "summon marker ~ ~ ~ {Tags:[\"markerdim13\"]}"
                    },
                    {
                      "type": "origins:execute_command",
                      "command": "execute in limeorigins:pocket_dim_13 run tp @s 500 97 500"
                    }
                  ]
                }
              },
              {
                "condition": {
                  "type": "origins:scoreboard",
                  "objective": "dim_owned",
                  "comparison": "==",
                  "compare_to": 14
                },
                "action": {
                  "type": "origins:and",
                  "actions": [
                    {
                      "type": "origins:execute_command",
                      "command": "summon marker ~ ~ ~ {Tags:[\"markerdim14\"]}"
                    },
                    {
                      "type": "origins:execute_command",
                      "command": "execute in limeorigins:pocket_dim_14 run tp @s 500 97 500"
                    }
                  ]
                }
              },
              {
                "condition": {
                  "type": "origins:scoreboard",
                  "objective": "dim_owned",
                  "comparison": "==",
                  "compare_to": 15
                },
                "action": {
                  "type": "origins:and",
                  "actions": [
                    {
                      "type": "origins:execute_command",
                      "command": "summon marker ~ ~ ~ {Tags:[\"markerdim15\"]}"
                    },
                    {
                      "type": "origins:execute_command",
                      "command": "execute in limeorigins:pocket_dim_15 run tp @s 500 97 500"
                    }
                  ]
                }
              },
              {
                "condition": {
                  "type": "origins:scoreboard",
                  "objective": "dim_owned",
                  "comparison": "==",
                  "compare_to": 16
                },
                "action": {
                  "type": "origins:and",
                  "actions": [
                    {
                      "type": "origins:execute_command",
                      "command": "summon marker ~ ~ ~ {Tags:[\"markerdim16\"]}"
                    },
                    {
                      "type": "origins:execute_command",
                      "command": "execute in limeorigins:pocket_dim_16 run tp @s 500 97 500"
                    }
                  ]
                }
              },
              {
                "condition": {
                  "type": "origins:scoreboard",
                  "objective": "dim_owned",
                  "comparison": "==",
                  "compare_to": 17
                },
                "action": {
                  "type": "origins:and",
                  "actions": [
                    {
                      "type": "origins:execute_command",
                      "command": "summon marker ~ ~ ~ {Tags:[\"markerdim17\"]}"
                    },
                    {
                      "type": "origins:execute_command",
                      "command": "execute in limeorigins:pocket_dim_17 run tp @s 500 97 500"
                    }
                  ]
                }
              },
              {
                "condition": {
                  "type": "origins:scoreboard",
                  "objective": "dim_owned",
                  "comparison": "==",
                  "compare_to": 18
                },
                "action": {
                  "type": "origins:and",
                  "actions": [
                    {
                      "type": "origins:execute_command",
                      "command": "summon marker ~ ~ ~ {Tags:[\"markerdim18\"]}"
                    },
                    {
                      "type": "origins:execute_command",
                      "command": "execute in limeorigins:pocket_dim_18 run tp @s 500 97 500"
                    }
                  ]
                }
              },
              {
                "condition": {
                  "type": "origins:scoreboard",
                  "objective": "dim_owned",
                  "comparison": "==",
                  "compare_to": 19
                },
                "action": {
                  "type": "origins:and",
                  "actions": [
                    {
                      "type": "origins:execute_command",
                      "command": "summon marker ~ ~ ~ {Tags:[\"markerdim19\"]}"
                    },
                    {
                      "type": "origins:execute_command",
                      "command": "execute in limeorigins:pocket_dim_19 run tp @s 500 97 500"
                    }
                  ]
                }
              },
              {
                "condition": {
                  "type": "origins:scoreboard",
                  "objective": "dim_owned",
                  "comparison": "==",
                  "compare_to": 20
                },
                "action": {
                  "type": "origins:and",
                  "actions": [
                    {
                      "type": "origins:execute_command",
                      "command": "summon marker ~ ~ ~ {Tags:[\"markerdim20\"]}"
                    },
                    {
                      "type": "origins:execute_command",
                      "command": "execute in limeorigins:pocket_dim_20 run tp @s 500 97 500"
                    }
                  ]
                }
              }
            ]
          }
        },
        {
          "type": "origins:delay",
          "ticks": 2,
          "action": {
            "type": "origins:play_sound",
            "sound": "minecraft:entity.enderman.teleport"
          }
        }
      ]
    },

    "else_action": {
      "type": "origins:and",
      "actions": [
        {
          "type": "origins:play_sound",
          "sound": "minecraft:entity.enderman.teleport"
        },
        {
          "type": "origins:if_else_list",
          "actions": [
            {
              "condition": {
                "type": "origins:scoreboard",
                "objective": "dim_owned",
                "comparison": "==",
                "compare_to": "1"
              },
              "action": {
                "type": "origins:and",
                "actions": [
                  {
                    "type": "origins:execute_command",
                    "command": "execute as @s run tp @e[type=marker, tag=markerdim1, limit=1]"
                  },
                  {
                    "type": "origins:execute_command",
                    "command": "kill @e[type=marker, tag=markerdim1]"
                  }
                ]
              }
            },
            {
              "condition": {
                "type": "origins:scoreboard",
                "objective": "dim_owned",
                "comparison": "==",
                "compare_to": "2"
              },
              "action": {
                "type": "origins:and",
                "actions": [
                  {
                    "type": "origins:execute_command",
                    "command": "execute as @s run tp @e[type=marker, tag=markerdim2, limit=1]"
                  },
                  {
                    "type": "origins:execute_command",
                    "command": "kill @e[type=marker, tag=markerdim2]"
                  }
                ]
              }
            },
            {
              "condition": {
                "type": "origins:scoreboard",
                "objective": "dim_owned",
                "comparison": "==",
                "compare_to": "3"
              },
              "action": {
                "type": "origins:and",
                "actions": [
                  {
                    "type": "origins:execute_command",
                    "command": "execute as @s run tp @e[type=marker, tag=markerdim3, limit=1]"
                  },
                  {
                    "type": "origins:execute_command",
                    "command": "kill @e[type=marker, tag=markerdim3]"
                  }
                ]
              }
            },
            {
              "condition": {
                "type": "origins:scoreboard",
                "objective": "dim_owned",
                "comparison": "==",
                "compare_to": "4"
              },
              "action": {
                "type": "origins:and",
                "actions": [
                  {
                    "type": "origins:execute_command",
                    "command": "execute as @s run tp @e[type=marker, tag=markerdim4, limit=1]"
                  },
                  {
                    "type": "origins:execute_command",
                    "command": "kill @e[type=marker, tag=markerdim4]"
                  }
                ]
              }
            },
            {
              "condition": {
                "type": "origins:scoreboard",
                "objective": "dim_owned",
                "comparison": "==",
                "compare_to": "5"
              },
              "action": {
                "type": "origins:and",
                "actions": [
                  {
                    "type": "origins:execute_command",
                    "command": "execute as @s run tp @e[type=marker, tag=markerdim5, limit=1]"
                  },
                  {
                    "type": "origins:execute_command",
                    "command": "kill @e[type=marker, tag=markerdim5]"
                  }
                ]
              }
            },
            {
              "condition": {
                "type": "origins:scoreboard",
                "objective": "dim_owned",
                "comparison": "==",
                "compare_to": "6"
              },
              "action": {
                "type": "origins:and",
                "actions": [
                  {
                    "type": "origins:execute_command",
                    "command": "execute as @s run tp @e[type=marker, tag=markerdim6, limit=1]"
                  },
                  {
                    "type": "origins:execute_command",
                    "command": "kill @e[type=marker, tag=markerdim6]"
                  }
                ]
              }
            },
            {
              "condition": {
                "type": "origins:scoreboard",
                "objective": "dim_owned",
                "comparison": "==",
                "compare_to": "7"
              },
              "action": {
                "type": "origins:and",
                "actions": [
                  {
                    "type": "origins:execute_command",
                    "command": "execute as @s run tp @e[type=marker, tag=markerdim7, limit=1]"
                  },
                  {
                    "type": "origins:execute_command",
                    "command": "kill @e[type=marker, tag=markerdim7]"
                  }
                ]
              }
            },
            {
              "condition": {
                "type": "origins:scoreboard",
                "objective": "dim_owned",
                "comparison": "==",
                "compare_to": "8"
              },
              "action": {
                "type": "origins:and",
                "actions": [
                  {
                    "type": "origins:execute_command",
                    "command": "execute as @s run tp @e[type=marker, tag=markerdim8, limit=1]"
                  },
                  {
                    "type": "origins:execute_command",
                    "command": "kill @e[type=marker, tag=markerdim8]"
                  }
                ]
              }
            },
            {
              "condition": {
                "type": "origins:scoreboard",
                "objective": "dim_owned",
                "comparison": "==",
                "compare_to": "9"
              },
              "action": {
                "type": "origins:and",
                "actions": [
                  {
                    "type": "origins:execute_command",
                    "command": "execute as @s run tp @e[type=marker, tag=markerdim9, limit=1]"
                  },
                  {
                    "type": "origins:execute_command",
                    "command": "kill @e[type=marker, tag=markerdim9]"
                  }
                ]
              }
            },
            {
              "condition": {
                "type": "origins:scoreboard",
                "objective": "dim_owned",
                "comparison": "==",
                "compare_to": "10"
              },
              "action": {
                "type": "origins:and",
                "actions": [
                  {
                    "type": "origins:execute_command",
                    "command": "execute as @s run tp @e[type=marker, tag=markerdim10, limit=1]"
                  },
                  {
                    "type": "origins:execute_command",
                    "command": "kill @e[type=marker, tag=markerdim10]"
                  }
                ]
              }
            },
            {
              "condition": {
                "type": "origins:scoreboard",
                "objective": "dim_owned",
                "comparison": "==",
                "compare_to": "11"
              },
              "action": {
                "type": "origins:and",
                "actions": [
                  {
                    "type": "origins:execute_command",
                    "command": "execute as @s run tp @e[type=marker, tag=markerdim11, limit=1]"
                  },
                  {
                    "type": "origins:execute_command",
                    "command": "kill @e[type=marker, tag=markerdim11]"
                  }
                ]
              }
            },
            {
              "condition": {
                "type": "origins:scoreboard",
                "objective": "dim_owned",
                "comparison": "==",
                "compare_to": "12"
              },
              "action": {
                "type": "origins:and",
                "actions": [
                  {
                    "type": "origins:execute_command",
                    "command": "execute as @s run tp @e[type=marker, tag=markerdim12, limit=1]"
                  },
                  {
                    "type": "origins:execute_command",
                    "command": "kill @e[type=marker, tag=markerdim12]"
                  }
                ]
              }
            },
            {
              "condition": {
                "type": "origins:scoreboard",
                "objective": "dim_owned",
                "comparison": "==",
                "compare_to": "13"
              },
              "action": {
                "type": "origins:and",
                "actions": [
                  {
                    "type": "origins:execute_command",
                    "command": "execute as @s run tp @e[type=marker, tag=markerdim13, limit=1]"
                  },
                  {
                    "type": "origins:execute_command",
                    "command": "kill @e[type=marker, tag=markerdim13]"
                  }
                ]
              }
            },
            {
              "condition": {
                "type": "origins:scoreboard",
                "objective": "dim_owned",
                "comparison": "==",
                "compare_to": "14"
              },
              "action": {
                "type": "origins:and",
                "actions": [
                  {
                    "type": "origins:execute_command",
                    "command": "execute as @s run tp @e[type=marker, tag=markerdim14, limit=1]"
                  },
                  {
                    "type": "origins:execute_command",
                    "command": "kill @e[type=marker, tag=markerdim14]"
                  }
                ]
              }
            },
            {
              "condition": {
                "type": "origins:scoreboard",
                "objective": "dim_owned",
                "comparison": "==",
                "compare_to": "15"
              },
              "action": {
                "type": "origins:and",
                "actions": [
                  {
                    "type": "origins:execute_command",
                    "command": "execute as @s run tp @e[type=marker, tag=markerdim15, limit=1]"
                  },
                  {
                    "type": "origins:execute_command",
                    "command": "kill @e[type=marker, tag=markerdim15]"
                  }
                ]
              }
            },
            {
              "condition": {
                "type": "origins:scoreboard",
                "objective": "dim_owned",
                "comparison": "==",
                "compare_to": "16"
              },
              "action": {
                "type": "origins:and",
                "actions": [
                  {
                    "type": "origins:execute_command",
                    "command": "execute as @s run tp @e[type=marker, tag=markerdim16, limit=1]"
                  },
                  {
                    "type": "origins:execute_command",
                    "command": "kill @e[type=marker, tag=markerdim16]"
                  }
                ]
              }
            },
            {
              "condition": {
                "type": "origins:scoreboard",
                "objective": "dim_owned",
                "comparison": "==",
                "compare_to": "17"
              },
              "action": {
                "type": "origins:and",
                "actions": [
                  {
                    "type": "origins:execute_command",
                    "command": "execute as @s run tp @e[type=marker, tag=markerdim17, limit=1]"
                  },
                  {
                    "type": "origins:execute_command",
                    "command": "kill @e[type=marker, tag=markerdim17]"
                  }
                ]
              }
            },
            {
              "condition": {
                "type": "origins:scoreboard",
                "objective": "dim_owned",
                "comparison": "==",
                "compare_to": "18"
              },
              "action": {
                "type": "origins:and",
                "actions": [
                  {
                    "type": "origins:execute_command",
                    "command": "execute as @s run tp @e[type=marker, tag=markerdim18, limit=1]"
                  },
                  {
                    "type": "origins:execute_command",
                    "command": "kill @e[type=marker, tag=markerdim18]"
                  }
                ]
              }
            },
            {
              "condition": {
                "type": "origins:scoreboard",
                "objective": "dim_owned",
                "comparison": "==",
                "compare_to": "19"
              },
              "action": {
                "type": "origins:and",
                "actions": [
                  {
                    "type": "origins:execute_command",
                    "command": "execute as @s run tp @e[type=marker, tag=markerdim19, limit=1]"
                  },
                  {
                    "type": "origins:execute_command",
                    "command": "kill @e[type=marker, tag=markerdim19]"
                  }
                ]
              }
            },
            {
              "condition": {
                "type": "origins:scoreboard",
                "objective": "dim_owned",
                "comparison": "==",
                "compare_to": "20"
              },
              "action": {
                "type": "origins:and",
                "actions": [
                  {
                    "type": "origins:execute_command",
                    "command": "execute as @s run tp @e[type=marker, tag=markerdim20, limit=1]"
                  },
                  {
                    "type": "origins:execute_command",
                    "command": "kill @e[type=marker, tag=markerdim20]"
                  }
                ]
              }
            }
          ]
        },
        {
          "type": "origins:delay",
          "ticks": 2,
          "action": {
            "type": "origins:play_sound",
            "sound": "minecraft:entity.enderman.teleport"
          }
        }
      ]
    }
  }
}